{
 "type": "1",
 "title": "Archivos para agregar registros",
 "description": "Archivos para agregar registros.",
 "printDescription": "Página para imprimir que muestra los archivos para agregar registros.",
 "listado": [
  {
   "name": "mAagregaHtml.html",
   "title": "agrega.html",
   "description": "Código de «agrega.html»."
  },
  {
   "name": "mBSrvProductoAgregaPhp.html",
   "title": "srv / SrvProductoAgrega.php",
   "description": "Código de «srv/SrvProductoAgrega.php»."
  },
  {
   "name": "mCproductoAgregaPhp.html",
   "title": "srv / dao / productoAgrega.php",
   "description": "Código de «srv/dao/productoAgrega.php»."
  },
  {
   "name": "mDarchivoAgregaPhp.html",
   "title": "srv / dao / archivoAgrega.php",
   "description": "Código de «srv/dao/archivoAgrega.php»."
  }
 ]
}