{
 "type": "1",
 "title": "Carpeta « lib / js »",
 "description": "Archivos de la carpeta «lib/js».",
 "printerDescription": "Página para imprimir de los archivos de la carpeta «lib/js».",
 "listado": [
    {
  "name": "m-errorEnWebSocket-js.html",
  "title": "lib / js / errorEnWebSocket.js",
  "description": "Código de «lib/js/errorEnWebSocket.js»."
 },
 {
  "name": "m-muestraError-js.html",
  "title": "lib / js / muestraError.js",
  "description": "Código de «lib/js/muestraError.js»."
 },
 {
  "name": "m-webSocketCerrado-js.html",
  "title": "lib / js / webSocketCerrado.js",
  "description": "Código de «lib/js/webSocketCerrado.js»."
 }
 ]
}