{
 "type": "1",
 "title": "Archivos para generar listados",
 "description": "Archivos para generar listados.",
 "printDescription": "Página para imprimir que muestra los archivos para generar listados",
 "listado": [
  {
   "name": "mAindexHtml.html",
   "title": "index.html",
   "description": "Código de «index.html»."
  },
  {
   "name": "mBSrvProductoConsultaPhp.html",
   "title": "srv / SrvProductoConsulta.php",
   "description": "Código de «srv/SrvProductoConsulta.php»."
  },
  {
   "name": "mCproductoConsultaPhp.html",
   "title": "srv / dao / productoConsulta.php",
   "description": "Código de «srv/dao/productoConsulta.php»."
  }
 ]
}